{
	"name": "PL_YourHippo_Process_WebHook_Result_files",
	"properties": {
		"activities": [
			{
				"name": "Get Result File List",
				"type": "GetMetadata",
				"dependsOn": [
					{
						"activity": "Does WebhookFiles Result files exists",
						"dependencyConditions": [
							"Succeeded"
						]
					}
				],
				"policy": {
					"timeout": "0.12:00:00",
					"retry": 0,
					"retryIntervalInSeconds": 30,
					"secureOutput": false,
					"secureInput": false
				},
				"userProperties": [],
				"typeProperties": {
					"dataset": {
						"referenceName": "DS_YourHippo_WebHook_Json_Result_File",
						"type": "DatasetReference"
					},
					"fieldList": [
						"childItems"
					],
					"storeSettings": {
						"type": "AzureBlobStorageReadSettings",
						"recursive": true,
						"enablePartitionDiscovery": false
					},
					"formatSettings": {
						"type": "JsonReadSettings"
					}
				}
			},
			{
				"name": "Process File List",
				"type": "ForEach",
				"dependsOn": [
					{
						"activity": "Get Result File List",
						"dependencyConditions": [
							"Succeeded"
						]
					}
				],
				"userProperties": [],
				"typeProperties": {
					"items": {
						"value": "@activity('Get Result File List').output.childItems",
						"type": "Expression"
					},
					"activities": [
						{
							"name": "Process Result Files",
							"type": "Copy",
							"dependsOn": [],
							"policy": {
								"timeout": "0.12:00:00",
								"retry": 0,
								"retryIntervalInSeconds": 30,
								"secureOutput": false,
								"secureInput": false
							},
							"userProperties": [],
							"typeProperties": {
								"source": {
									"type": "JsonSource",
									"storeSettings": {
										"type": "AzureBlobStorageReadSettings",
										"recursive": false,
										"wildcardFileName": {
											"value": "@item().Name",
											"type": "Expression"
										},
										"enablePartitionDiscovery": false
									},
									"formatSettings": {
										"type": "JsonReadSettings"
									}
								},
								"sink": {
									"type": "AzureSqlSink",
									"writeBehavior": "upsert",
									"upsertSettings": {
										"useTempDB": true,
										"keys": [
											"ResultID"
										]
									},
									"sqlWriterUseTableLock": false,
									"disableMetricsCollection": false
								},
								"enableStaging": false,
								"translator": {
									"type": "TabularTranslator",
									"mappings": [
										{
											"source": {
												"path": "$['data']['result']['id']"
											},
											"sink": {
												"name": "ResultID",
												"type": "Int32"
											}
										},
										{
											"source": {
												"path": "$['data']['result']['passed']"
											},
											"sink": {
												"name": "Passed",
												"type": "Boolean"
											}
										},
										{
											"source": {
												"path": "$['data']['result']['grade']"
											},
											"sink": {
												"name": "Grade",
												"type": "String"
											}
										},
										{
											"source": {
												"path": "$['data']['result']['score']"
											},
											"sink": {
												"name": "Score",
												"type": "Decimal"
											}
										},
										{
											"source": {
												"path": "$['data']['result']['completed_at']"
											},
											"sink": {
												"name": "CompletedAt",
												"type": "DateTime"
											}
										},
										{
											"source": {
												"path": "$['data']['result']['expires_at']"
											},
											"sink": {
												"name": "ExpiresAt",
												"type": "DateTime"
											}
										},
										{
											"source": {
												"path": "$['data']['result']['has_expired']"
											},
											"sink": {
												"name": "HasExpired",
												"type": "Boolean"
											}
										},
										{
											"source": {
												"path": "$['data']['result']['course']['id']"
											},
											"sink": {
												"name": "CourseID",
												"type": "Int32"
											}
										},
										{
											"source": {
												"path": "$['data']['result']['user']['id']"
											},
											"sink": {
												"name": "UserID",
												"type": "String"
											}
										}
									],
									"collectionReference": ""
								}
							},
							"inputs": [
								{
									"referenceName": "DS_YourHippo_WebHook_Json_Result_File",
									"type": "DatasetReference"
								}
							],
							"outputs": [
								{
									"referenceName": "DS_AH2_TRANSFORM_DB",
									"type": "DatasetReference",
									"parameters": {
										"Schema": "YourHippo",
										"Table": "Results"
									}
								}
							]
						}
					]
				}
			},
			{
				"name": "Archive Files",
				"type": "Copy",
				"dependsOn": [
					{
						"activity": "Process File List",
						"dependencyConditions": [
							"Succeeded"
						]
					}
				],
				"policy": {
					"timeout": "0.12:00:00",
					"retry": 0,
					"retryIntervalInSeconds": 30,
					"secureOutput": false,
					"secureInput": false
				},
				"userProperties": [],
				"typeProperties": {
					"source": {
						"type": "BinarySource",
						"storeSettings": {
							"type": "AzureBlobStorageReadSettings",
							"recursive": false,
							"deleteFilesAfterCompletion": true
						},
						"formatSettings": {
							"type": "BinaryReadSettings"
						}
					},
					"sink": {
						"type": "BinarySink",
						"storeSettings": {
							"type": "AzureBlobStorageWriteSettings"
						}
					},
					"enableStaging": false
				},
				"inputs": [
					{
						"referenceName": "DS_YourHippo_WebHook_Files",
						"type": "DatasetReference",
						"parameters": {
							"Folder": {
								"value": "@concat('WebhookFiles', '/', 'Result')",
								"type": "Expression"
							}
						}
					}
				],
				"outputs": [
					{
						"referenceName": "DS_YourHippo_WebHook_Files",
						"type": "DatasetReference",
						"parameters": {
							"Folder": {
								"value": "@concat('WebhookFiles', '/', 'Archive', '/', 'Result')",
								"type": "Expression"
							}
						}
					}
				]
			},
			{
				"name": "Does WebhookFiles Result files exists",
				"description": "Checks there are files to process. If there are it will succeeds and carry on, if not it fails with custom failure message",
				"type": "Lookup",
				"dependsOn": [],
				"policy": {
					"timeout": "0.12:00:00",
					"retry": 0,
					"retryIntervalInSeconds": 30,
					"secureOutput": false,
					"secureInput": false
				},
				"userProperties": [],
				"typeProperties": {
					"source": {
						"type": "JsonSource",
						"storeSettings": {
							"type": "AzureBlobStorageReadSettings",
							"recursive": false,
							"wildcardFileName": "webhook$result*.json",
							"enablePartitionDiscovery": false
						},
						"formatSettings": {
							"type": "JsonReadSettings"
						}
					},
					"dataset": {
						"referenceName": "DS_YourHippo_WebHook_Json_Result_File",
						"type": "DatasetReference"
					}
				}
			},
			{
				"name": "No Files failure",
				"type": "Fail",
				"dependsOn": [
					{
						"activity": "Does WebhookFiles Result files exists",
						"dependencyConditions": [
							"Failed"
						]
					}
				],
				"userProperties": [],
				"typeProperties": {
					"message": "No Result files to process",
					"errorCode": "404"
				}
			}
		],
		"folder": {
			"name": "YourHippo/Child Pipelines"
		},
		"annotations": []
	}
}